Workbook

Sheet Read me
A1: LLM API budget — the exam / judge / generate / fine-tune loop
A3: SHEETS, IN READING ORDER
A4: Steps the loop, and which steps cost API money
A5: Glossary what each counted thing is — read before the numbers
A6: Prices provider rates, transcribed 2026-09-18, with sources
A7: Assumptions our workload. The only cells you normally change
A8: Volume tokens per cycle, all formulas
A9: Per cycle THE ANSWER: cost of one trip round the loop
A10: Run rate the same x a monthly cadence, if you want it
A11: Scenarios how the bill moves with how much training text you generate
A13: COLOUR
A14: Blue text a hardcoded input Black text a formula
... A26: Human time, which is the real limit on how many cycles you can actually run.

Sheet Steps
A1: The loop
A2: Step 0 happens once, up front. Steps 1-5 are the cycle: it ends where it began, with a better checkpoint sitting the same exam. Yellow rows are inside the cycle; green means no API cost.
A4: # | B4: Step | C4: Who does it | D4: What goes in | E4: What comes out | F4: API cost?
A5: 0 | B5: Write the exam | C5: an LLM, via API | D5: a topic brief + rubric + example questions | E5: the exam question bank: questions across every topic, each with a reference answer | F5: YES — up front
A6: 1 | B6: Sit the exam | C6: the checkpoint, on our RTX 5090 | D6: the exam questions | E6: answer scripts — what the model wrote, with its explanation | F6: No — $0
A7: 2 | B7: Judge the answers | C7: an LLM, via API | D7: each answer script + the rubric | E7: a score per topic, and written evaluation of what went wrong | F7: YES — cost 1 of 2
A8: 3 | B8: Choose the topic to improve | C8: a human, reading the dashboard | D8: the per-topic scores and the judge's written evaluation | E8: one topic picked, and a skill spec naming what is missing | F8: tiny — a summarising call
A9: 4 | B9: Generate the dataset | C9: an LLM, via API | D9: the approved skill spec, and nothing else | E9: training documents — prose passages teaching that topic | F9: YES — cost 2 of 2
A10: 5 | B10: Fine-tune and resubmit | C10: whoever owns the training run | D10: the generated documents, mixed into training | E10: a new checkpoint, submitted to the board | F10: No — $0
A11: ↻ | B11: back to step 1 — sit the same exam again | E11: the before/after that says whether it worked
A13: WHAT ALSO RUNS, BUT IS NOT PART OF THIS LOOP:
A14: The standard benchmarks (MMLU, HellaSwag, ARC...) still run on every submission and still cost $0 in API —
A15: they are scored by loglikelihood on our own GPU. They stay on the board as the comparable, public-protocol
A16: number. scripts/diagnose.py still explains them for free. But they do not drive this loop: the exam does.
A18: THE ONE RULE THIS LOOP STILL NEEDS:
A19: The exam bank is split in half by content hash, exactly as the benchmarks are.
A20: The REPORT half produces the score you publish. The DIAGNOSE half is the only half step 3 may read.
A21: Without that, step 4 generates training data aimed at the questions step 2 just marked, the next score goes up,
A22: and the model has learned nothing. The split is what makes the before/after in step 5 mean something.
A23: Note this is stronger than it sounds here: the exam is OUR OWN generated questions, so nothing external
A24: protects it. The split is the only thing standing between this loop and training on its own test.

Sheet Glossary
A1: What each counted thing is
A2: None of these is called an "item". They are not interchangeable.
A4: Term | B4: Step | C4: What exactly it is | D4: Roughly | E4: Why it matters
A5: topic | B5: 0 | C5: A human-readable subject area: economics, law, medicine, mathematics. The thing you actually want to say we are weak in. | D5: ~15 of them | E5: The unit the whole loop reports and acts in.
A6: exam question | B6: 0 | C6: One AI-written question in our own benchmark, with a reference answer and rubric. Written once, reused every cycle. | D6: ~400 tok to draft | E6: Paid once per bank. Refresh occasionally, not per cycle.
A7: answer script | B7: 1-2 | C7: What ONE model wrote for ONE exam question, including the explanation we asked it for. | D7: ~300 tok written | E7: Produced free on our GPU. Graded by one API call. Their count drives the judging bill.
A8: rubric score | B8: 2 | C8: The judge's mark on one answer script, per rubric dimension, plus a short written justification of the mark. | D8: ~200 tok written | E8: Averaged per topic, this IS the score. The justifications are what step 3 reads.
A9: skill spec | B9: 3 | C9: One to three sentences naming what is missing in the chosen topic — not the questions. Written by summarising the judge's justifications, approved by a human. | D9: ~120 tok | E9: THE AIRLOCK. The only thing the generator ever sees. No exam question crosses it.
A10: training document | B10: 4 | C10: One generated prose passage teaching the skill in the spec. A short explainer or reference text, NOT a question-and-answer pair. | D10: ~800 tok | E10: The biggest line in the budget: pure generated output.
A11: cycle | B11: 1-5 | C11: One pass: sit the exam, judge it, pick a topic, generate data, fine-tune, resubmit. | D11: — | E11: The unit this workbook prices.

Sheet Prices
A1: API price list — transcribed from provider pricing pages
A2: Blue = transcribed. Batch columns are formulas: both providers state 50% off input and output.
A4: Checked | B4: 2026-09-18
A5: Anthropic source | B5: https://platform.claude.com/docs/en/about-claude/pricing
A6: OpenAI source | B6: https://developers.openai.com/api/docs/pricing
A7: Batch discount | B7: 0.5 | C7: Stated by both providers.
A9: Provider | B9: Model | C9: Input $/MTok | D9: Output $/MTok | E9: Cache read $/MTok | F9: Batch input $/MTok | G9: Batch output $/MTok | H9: Token factor | I9: Note
A10: Anthropic | B10: Claude Fable 5.1 | C10: 10 | D10: 50 | E10: 0.25 | F10: =C10*(1-$B$7) -> 5 | G10: =D10*(1-$B$7) -> 25 | H10: 1.3 | I10: Flagship.
A11: Anthropic | B11: Claude Opus 5 | C11: 5 | D11: 25 | E11: 0.5 | F11: =C11*(1-$B$7) -> 2.5 | G11: =D11*(1-$B$7) -> 12.5 | H11: 1.3 | I11: Strongest reasoning at a sane price.
A12: Anthropic | B12: Claude Sonnet 5 | C12: 2 | D12: 10 | E12: 0.2 | F12: =C12*(1-$B$7) -> 1 | G12: =D12*(1-$B$7) -> 5 | H12: 1.3 | I12: $2/$10 is now standard.
A13: Anthropic | B13: Claude Sonnet 4.6 | C13: 3 | D13: 15 | E13: 0.3 | F13: =C13*(1-$B$7) -> 1.5 | G13: =D13*(1-$B$7) -> 7.5 | H13: 1 | I13: Older tokenizer.
A14: Anthropic | B14: Claude Haiku 4.5 | C14: 1 | D14: 5 | E14: 0.1 | F14: =C14*(1-$B$7) -> 0.5 | G14: =D14*(1-$B$7) -> 2.5 | H14: 1 | I14: Older tokenizer. Cheapest for bulk.
A15: OpenAI | B15: gpt-6-astra | C15: 10 | D15: 50 | E15: 1 | F15: =C15*(1-$B$7) -> 5 | G15: =D15*(1-$B$7) -> 25 | H15: 1 | I15: Flagship.
A16: OpenAI | B16: gpt-5.6-sol | C16: 4 | D16: 20 | E16: 0.4 | F16: =C16*(1-$B$7) -> 2 | G16: =D16*(1-$B$7) -> 10 | H16: 1 | I16: High-capability tier.
A17: OpenAI | B17: gpt-5.6-terra | C17: 2 | D17: 12 | E17: 0.2 | F17: =C17*(1-$B$7) -> 1 | G17: =D17*(1-$B$7) -> 6 | H17: 1 | I17: Mid tier.
A18: OpenAI | B18: gpt-5.6-luna | C18: 0.2 | D18: 1.2 | E18: 0.02 | F18: =C18*(1-$B$7) -> 0.1 | G18: =D18*(1-$B$7) -> 0.6 | H18: 1 | I18: Cheapest capable tier.
A19: OpenAI | B19: gpt-5.5 | C19: 5 | D19: 30 | E19: 0.5 | F19: =C19*(1-$B$7) -> 2.5 | G19: =D19*(1-$B$7) -> 15 | H19: 1 | I19: Previous flagship tier.
A20: OpenAI | B20: gpt-5.4-mini | C20: 0.75 | D20: 4.5 | E20: 0.075 | F20: =C20*(1-$B$7) -> 0.375 | G20: =D20*(1-$B$7) -> 2.25 | H20: 1 | I20: Small tier.
A21: OpenAI | B21: gpt-5-mini | C21: 0.25 | D21: 2 | E21: 0.025 | F21: =C21*(1-$B$7) -> 0.125 | G21: =D21*(1-$B$7) -> 1 | H21: 1 | I21: Older small tier.
A22: OpenAI | B22: gpt-5-nano | C22: 0.05 | D22: 0.4 | E22: 0.005 | F22: =C22*(1-$B$7) -> 0.025 | G22: =D22*(1-$B$7) -> 0.2 | H22: 1 | I22: Cheapest listed.
A24: Token factor: Anthropic states Claude 4.7-and-later models use a newer tokenizer producing ~30% MORE tokens for the same text; Sonnet 4.6 and earlier use the older one. This column corrects for it so comparisons are per unit of TEXT.
A25: INFERRED, not stated: the docs name "4.7 and later" and "Sonnet 4.6 and earlier" without naming Sonnet 5 or Opus 5. The 1.30 factors follow from version ordering. If wrong, those two are ~23% cheaper than shown.
A26: OpenAI factors are 1.00 as the baseline. Neither provider states how the tokenizers compare, so cross-provider figures carry roughly +/-10% of tokenizer uncertainty.
A27: Batch turnaround, Anthropic (verified): most batches finish within 1 hour; results at completion or 24h, whichever first; expire at 24h. Limit 100,000 requests or 256 MB per batch. OpenAI's window not verified here.
A28: Prompt caching is not modelled. It stacks with batch and would only reduce these numbers — the judge's rubric is the obvious thing to cache, since it repeats on every answer script.

Sheet Assumptions
A1: Workload assumptions — edit the yellow cells
A2: Estimates of OUR workload, not published figures. Terms are on the Glossary sheet. Token counts are in the OLDER tokenizer; the Per cycle sheet scales them per model.
A4: Driver | B4: Value | C4: Unit | D4: What it means
A5: THE EXAM — shared by every step
A6: Topics | B6: 15 | C6: topics | D6: Economics, law, medicine, mathematics... the categories you want the score reported in.
A7: Exam questions per topic | B7: 60 | C7: questions | D7: Size of the bank per topic. Split in half: ~30 give the published score, ~30 feed step 3.
A9: STEP 0 — write the exam (paid once, refreshed occasionally)
A10: Candidates drafted per final question | B10: 1.5 | C10: ratio | D10: We draft more than we keep and a human curates. 1.5 means draft 90 per topic to keep 60.
A11: Tokens per drafted candidate question | B11: 400 | C11: tokens | D11: The question, a reference answer, and rubric hints.
A12: Candidate questions per drafting request | B12: 5 | C12: questions | D12: How many candidates we ask for in one API call.
A13: Brief sent with each drafting request | B13: 900 | C13: tokens | D13: Topic description, rubric, and example questions, so drafts are on-target and varied.
A15: STEP 2 — judge the answers
A16: Models judged per cycle | B16: 1 | C16: models | D16: Set to 2 to judge the new checkpoint and its parent together for a clean before/after.
A17: Tokens sent to the judge per answer script | B17: 1100 | C17: tokens | D17: Rubric ~400 + question ~100 + reference answer ~150 + the model's written answer ~300 + instructions ~150.
A18: Tokens written by the judge per answer script | B18: 200 | C18: tokens | D18: A mark per rubric dimension plus a short written justification. The justifications are what step 3 reads.
A20: STEP 3 — choose the topic and write the skill spec
A21: Judge justifications read per cycle | B21: 40 | C21: justifications | D21: From the chosen topic's DIAGNOSE half only. Enough to see the pattern.
A22: Tokens per justification read | B22: 250 | C22: tokens | D22: The judge's written reasoning on one answer script.
A23: Instructions sent with the summarising request | B23: 600 | C23: tokens | D23: Task description and output schema.
A24: Tokens written per skill spec | B24: 500 | C24: tokens | D24: The spec sentence, the patterns seen, and the share of failures it explains.
A26: STEP 4 — generate the dataset
A27: Topics improved per cycle | B27: 1 | C27: topics | D27: You pick one topic per cycle. Raise it if you want to attack several at once.
A28: Training documents per topic | B28: 1000 | C28: documents | D28: How many prose passages we generate for the chosen topic. THE MAIN COST LEVER.
A29: Tokens per training document | B29: 800 | C29: tokens | D29: Length of one passage. 800 tokens is roughly 600 words of explainer prose.
A30: Training documents per API request | B30: 2 | C30: documents | D30: How many we ask for in one call. Long outputs, so only a couple fit.
A31: Instructions sent with each generation request | B31: 700 | C31: tokens | D31: Format rules + the approved spec + a style constraint, repeated on every request.
A33: RUN RATE — used only by the 'Run rate' sheet
A34: Cycles per month | B34: 4 | C34: cycles | D34: How many times a month you go round the loop.

Sheet Volume
A1: Token volume
A2: Green = pulled from Assumptions. Nothing typed in by hand.
A4: When | B4: Step | C4: API requests | D4: Input tokens | E4: Output tokens | F4: How it is derived
A5: Once, up front | B5: 0 · Write the exam | C5: =(Assumptions!$B$6*Assumptions!$B$7*Assumptions!$B$10)/Assumptions!$B$12 -> 270 | D5: =C5*Assumptions!$B$13 -> 243000 | E5: =(Assumptions!$B$6*Assumptions!$B$7*Assumptions!$B$10)*Assumptions!$B$11 -> 540000 | F5: topics x questions x draft ratio = candidates; / candidates per request
A6: Every cycle | B6: 2 · Judge the answers | C6: =(Assumptions!$B$16*Assumptions!$B$6*Assumptions!$B$7) -> 900 | D6: =C6*Assumptions!$B$17 -> 990000 | E6: =C6*Assumptions!$B$18 -> 180000 | F6: models x topics x questions = answer scripts, one request each
A7: Every cycle | B7: 3 · Choose topic, write the spec | C7: =1 -> 1 | D7: =Assumptions!$B$21*Assumptions!$B$22+Assumptions!$B$23 -> 10600 | E7: =Assumptions!$B$24 -> 500 | F7: one summarising call over the chosen topic's diagnose-half justifications
A8: Every cycle | B8: 4 · Generate the dataset | C8: =(Assumptions!$B$27*Assumptions!$B$28/Assumptions!$B$30) -> 500 | D8: =C8*Assumptions!$B$31 -> 350000 | E8: =Assumptions!$B$27*Assumptions!$B$28*Assumptions!$B$29 -> 800000 | F8: topics x documents each / documents per request
B9: Steps 1 and 5 run on our own GPU and appear nowhere above.

Sheet Per cycle
A1: Cost of ONE cycle — batch pricing
A2: A cycle is: sit the exam, judge it, pick a topic, generate the dataset. Change a model name in the yellow cells to any model on Prices, spelled exactly.
A4: When | B4: Step | C4: Model | D4: Input tok | E4: Output tok | F4: Token factor | G4: Batch $/MTok in | H4: Batch $/MTok out | I4: Cost in | J4: Cost out | K4: BATCH TOTAL | L4: Standard total
A5: Anthropic
A6: Once, up front | B6: 0 · Write the exam | C6: Claude Opus 5 | D6: =Volume!D5 -> 243000 | E6: =Volume!E5 -> 540000 | F6: =INDEX(Prices!$H$10:$H$22,MATCH($C6,Prices!$B$10:$B$22,0)) -> 1.3 | G6: =INDEX(Prices!$F$10:$F$22,MATCH($C6,Prices!$B$10:$B$22,0)) -> 2.5 | H6: =INDEX(Prices!$G$10:$G$22,MATCH($C6,Prices!$B$10:$B$22,0)) -> 12.5 | I6: =D6*F6*G6/1000000 -> 0.78975 | J6: =E6*F6*H6/1000000 -> 8.775 | K6: =I6+J6 -> 9.56475 | L6: =D6*F6*INDEX(Prices!$C$10:$C$22,MATCH($C6,Prices!$B$10:$B$22,0))/1000000+E6*F6*INDEX(Prices!$D$10:$D$22,MATCH($C6,Prices!$B$10:$B$22,0))/1000000 -> 19.1295
A7: Every cycle | B7: 2 · Judge the answers | C7: Claude Opus 5 | D7: =Volume!D6 -> 990000 | E7: =Volume!E6 -> 180000 | F7: =INDEX(Prices!$H$10:$H$22,MATCH($C7,Prices!$B$10:$B$22,0)) -> 1.3 | G7: =INDEX(Prices!$F$10:$F$22,MATCH($C7,Prices!$B$10:$B$22,0)) -> 2.5 | H7: =INDEX(Prices!$G$10:$G$22,MATCH($C7,Prices!$B$10:$B$22,0)) -> 12.5 | I7: =D7*F7*G7/1000000 -> 3.2175 | J7: =E7*F7*H7/1000000 -> 2.925 | K7: =I7+J7 -> 6.1425 | L7: =D7*F7*INDEX(Prices!$C$10:$C$22,MATCH($C7,Prices!$B$10:$B$22,0))/1000000+E7*F7*INDEX(Prices!$D$10:$D$22,MATCH($C7,Prices!$B$10:$B$22,0))/1000000 -> 12.285
A8: Every cycle | B8: 3 · Choose topic, write the spec | C8: Claude Opus 5 | D8: =Volume!D7 -> 10600 | E8: =Volume!E7 -> 500 | F8: =INDEX(Prices!$H$10:$H$22,MATCH($C8,Prices!$B$10:$B$22,0)) -> 1.3 | G8: =INDEX(Prices!$F$10:$F$22,MATCH($C8,Prices!$B$10:$B$22,0)) -> 2.5 | H8: =INDEX(Prices!$G$10:$G$22,MATCH($C8,Prices!$B$10:$B$22,0)) -> 12.5 | I8: =D8*F8*G8/1000000 -> 0.03445 | J8: =E8*F8*H8/1000000 -> 0.008125 | K8: =I8+J8 -> 0.042575 | L8: =D8*F8*INDEX(Prices!$C$10:$C$22,MATCH($C8,Prices!$B$10:$B$22,0))/1000000+E8*F8*INDEX(Prices!$D$10:$D$22,MATCH($C8,Prices!$B$10:$B$22,0))/1000000 -> 0.08515
A9: Every cycle | B9: 4 · Generate the dataset | C9: Claude Sonnet 5 | D9: =Volume!D8 -> 350000 | E9: =Volume!E8 -> 800000 | F9: =INDEX(Prices!$H$10:$H$22,MATCH($C9,Prices!$B$10:$B$22,0)) -> 1.3 | G9: =INDEX(Prices!$F$10:$F$22,MATCH($C9,Prices!$B$10:$B$22,0)) -> 1 | H9: =INDEX(Prices!$G$10:$G$22,MATCH($C9,Prices!$B$10:$B$22,0)) -> 5 | I9: =D9*F9*G9/1000000 -> 0.455 | J9: =E9*F9*H9/1000000 -> 5.2 | K9: =I9+J9 -> 5.655 | L9: =D9*F9*INDEX(Prices!$C$10:$C$22,MATCH($C9,Prices!$B$10:$B$22,0))/1000000+E9*F9*INDEX(Prices!$D$10:$D$22,MATCH($C9,Prices!$B$10:$B$22,0))/1000000 -> 11.31
B10: Anthropic — ONE CYCLE (steps 2 + 3 + 4) | K10: =K7+K8+K9 -> 11.840075 | L10: =L7+L8+L9 -> 23.68015
B11: Anthropic — THE EXAM, paid once (step 0) | K11: =K6 -> 9.56475 | L11: =L6 -> 19.1295
A13: OpenAI
A14: Once, up front | B14: 0 · Write the exam | C14: gpt-5.6-sol | D14: =Volume!D5 -> 243000 | E14: =Volume!E5 -> 540000 | F14: =INDEX(Prices!$H$10:$H$22,MATCH($C14,Prices!$B$10:$B$22,0)) -> 1 | G14: =INDEX(Prices!$F$10:$F$22,MATCH($C14,Prices!$B$10:$B$22,0)) -> 2 | H14: =INDEX(Prices!$G$10:$G$22,MATCH($C14,Prices!$B$10:$B$22,0)) -> 10 | I14: =D14*F14*G14/1000000 -> 0.486 | J14: =E14*F14*H14/1000000 -> 5.4 | K14: =I14+J14 -> 5.886 | L14: =D14*F14*INDEX(Prices!$C$10:$C$22,MATCH($C14,Prices!$B$10:$B$22,0))/1000000+E14*F14*INDEX(Prices!$D$10:$D$22,MATCH($C14,Prices!$B$10:$B$22,0))/1000000 -> 11.772
A15: Every cycle | B15: 2 · Judge the answers | C15: gpt-5.6-sol | D15: =Volume!D6 -> 990000 | E15: =Volume!E6 -> 180000 | F15: =INDEX(Prices!$H$10:$H$22,MATCH($C15,Prices!$B$10:$B$22,0)) -> 1 | G15: =INDEX(Prices!$F$10:$F$22,MATCH($C15,Prices!$B$10:$B$22,0)) -> 2 | H15: =INDEX(Prices!$G$10:$G$22,MATCH($C15,Prices!$B$10:$B$22,0)) -> 10 | I15: =D15*F15*G15/1000000 -> 1.98 | J15: =E15*F15*H15/1000000 -> 1.8 | K15: =I15+J15 -> 3.78 | L15: =D15*F15*INDEX(Prices!$C$10:$C$22,MATCH($C15,Prices!$B$10:$B$22,0))/1000000+E15*F15*INDEX(Prices!$D$10:$D$22,MATCH($C15,Prices!$B$10:$B$22,0))/1000000 -> 7.56
A16: Every cycle | B16: 3 · Choose topic, write the spec | C16: gpt-5.6-sol | D16: =Volume!D7 -> 10600 | E16: =Volume!E7 -> 500 | F16: =INDEX(Prices!$H$10:$H$22,MATCH($C16,Prices!$B$10:$B$22,0)) -> 1 | G16: =INDEX(Prices!$F$10:$F$22,MATCH($C16,Prices!$B$10:$B$22,0)) -> 2 | H16: =INDEX(Prices!$G$10:$G$22,MATCH($C16,Prices!$B$10:$B$22,0)) -> 10 | I16: =D16*F16*G16/1000000 -> 0.0212 | J16: =E16*F16*H16/1000000 -> 0.005 | K16: =I16+J16 -> 0.0262 | L16: =D16*F16*INDEX(Prices!$C$10:$C$22,MATCH($C16,Prices!$B$10:$B$22,0))/1000000+E16*F16*INDEX(Prices!$D$10:$D$22,MATCH($C16,Prices!$B$10:$B$22,0))/1000000 -> 0.0524
A17: Every cycle | B17: 4 · Generate the dataset | C17: gpt-5.6-terra | D17: =Volume!D8 -> 350000 | E17: =Volume!E8 -> 800000 | F17: =INDEX(Prices!$H$10:$H$22,MATCH($C17,Prices!$B$10:$B$22,0)) -> 1 | G17: =INDEX(Prices!$F$10:$F$22,MATCH($C17,Prices!$B$10:$B$22,0)) -> 1 | H17: =INDEX(Prices!$G$10:$G$22,MATCH($C17,Prices!$B$10:$B$22,0)) -> 6 | I17: =D17*F17*G17/1000000 -> 0.35 | J17: =E17*F17*H17/1000000 -> 4.8 | K17: =I17+J17 -> 5.15 | L17: =D17*F17*INDEX(Prices!$C$10:$C$22,MATCH($C17,Prices!$B$10:$B$22,0))/1000000+E17*F17*INDEX(Prices!$D$10:$D$22,MATCH($C17,Prices!$B$10:$B$22,0))/1000000 -> 10.3
B18: OpenAI — ONE CYCLE (steps 2 + 3 + 4) | K18: =K15+K16+K17 -> 8.9562 | L18: =L15+L16+L17 -> 17.9124
B19: OpenAI — THE EXAM, paid once (step 0) | K19: =K14 -> 5.886 | L19: =L14 -> 11.772
B21: Cost = tokens x token factor x $/MTok / 1,000,000. The token factor corrects for Anthropic's newer tokenizer; see Prices.
B22: Steps 1 (sit the exam) and 5 (fine-tune) cost nothing in API — they run on our own GPU.
B23: The judge is a strong model on purpose. Its score lands on the board, so a cheap judge that grades confidently and wrongly costs more than it saves. Drop to a cheaper one only after the human-agreement check (Cohen's kappa) says it grades the same.
B24: Pin the judge's dated model ID and record it, the rubric hash and the prompt hash in provenance. A vendor silently updating the model behind an alias means last cycle's scores stop being comparable to this one's — the unpinned-transformers failure again.

Sheet Run rate
A1: If you want a monthly figure
A2: Per-cycle cost from the 'Per cycle' sheet x the cadence on Assumptions.
A4: Provider | B4: Cycles/mo | C4: Per cycle | D4: Per month | E4: The exam (once) | F4: First month | G4: 12 months
A5: Anthropic | B5: =Assumptions!$B$34 -> 4 | C5: ='Per cycle'!K10 -> 11.840075 | D5: =B5*C5 -> 47.3603 | E5: ='Per cycle'!K11 -> 9.56475 | F5: =D5+E5 -> 56.92505 | G5: =12*D5+E5 -> 577.88835
A6: OpenAI | B6: =Assumptions!$B$34 -> 4 | C6: ='Per cycle'!K18 -> 8.9562 | D6: =B6*C6 -> 35.8248 | E6: ='Per cycle'!K19 -> 5.886 | F6: =D6+E6 -> 41.7108 | G6: =12*D6+E6 -> 435.7836

Sheet Scenarios
A1: The lever that moves the bill: how much training text you generate
A2: Cost of step 4 for ONE cycle, at four models. Everything else is rounding error beside it.
A4: Scenario | B4: Docs per topic | C4: Topics | D4: Documents | E4: Training tokens | F4: Claude Sonnet 5 | G4: Claude Haiku 4.5 | H4: gpt-5.6-terra | I4: gpt-5.6-luna
A5: Light — a nudge | B5: 250 | C5: 1 | D5: =B5*C5 -> 250 | E5: =D5*Assumptions!$B$29 -> 200000 | F5: =E5*INDEX(Prices!$H$10:$H$22,MATCH(F$4,Prices!$B$10:$B$22,0))*INDEX(Prices!$G$10:$G$22,MATCH(F$4,Prices!$B$10:$B$22,0))/1000000+(D5/Assumptions!$B$30)*Assumptions!$B$31*INDEX(Prices!$H$10:$H$22,MATCH(F$4,Prices!$B$10:$B$22,0))*INDEX(Prices!$F$10:$F$22,MATCH(F$4,Prices!$B$10:$B$22,0))/1000000 -> 1.41375 | G5: =E5*INDEX(Prices!$H$10:$H$22,MATCH(G$4,Prices!$B$10:$B$22,0))*INDEX(Prices!$G$10:$G$22,MATCH(G$4,Prices!$B$10:$B$22,0))/1000000+(D5/Assumptions!$B$30)*Assumptions!$B$31*INDEX(Prices!$H$10:$H$22,MATCH(G$4,Prices!$B$10:$B$22,0))*INDEX(Prices!$F$10:$F$22,MATCH(G$4,Prices!$B$10:$B$22,0))/1000000 -> 0.54375 | H5: =E5*INDEX(Prices!$H$10:$H$22,MATCH(H$4,Prices!$B$10:$B$22,0))*INDEX(Prices!$G$10:$G$22,MATCH(H$4,Prices!$B$10:$B$22,0))/1000000+(D5/Assumptions!$B$30)*Assumptions!$B$31*INDEX(Prices!$H$10:$H$22,MATCH(H$4,Prices!$B$10:$B$22,0))*INDEX(Prices!$F$10:$F$22,MATCH(H$4,Prices!$B$10:$B$22,0))/1000000 -> 1.2875 | I5: =E5*INDEX(Prices!$H$10:$H$22,MATCH(I$4,Prices!$B$10:$B$22,0))*INDEX(Prices!$G$10:$G$22,MATCH(I$4,Prices!$B$10:$B$22,0))/1000000+(D5/Assumptions!$B$30)*Assumptions!$B$31*INDEX(Prices!$H$10:$H$22,MATCH(I$4,Prices!$B$10:$B$22,0))*INDEX(Prices!$F$10:$F$22,MATCH(I$4,Prices!$B$10:$B$22,0))/1000000 -> 0.12875
A6: Base (Assumptions) | B6: 1000 | C6: 1 | D6: =B6*C6 -> 1000 | E6: =D6*Assumptions!$B$29 -> 800000 | F6: =E6*INDEX(Prices!$H$10:$H$22,MATCH(F$4,Prices!$B$10:$B$22,0))*INDEX(Prices!$G$10:$G$22,MATCH(F$4,Prices!$B$10:$B$22,0))/1000000+(D6/Assumptions!$B$30)*Assumptions!$B$31*INDEX(Prices!$H$10:$H$22,MATCH(F$4,Prices!$B$10:$B$22,0))*INDEX(Prices!$F$10:$F$22,MATCH(F$4,Prices!$B$10:$B$22,0))/1000000 -> 5.655 | G6: =E6*INDEX(Prices!$H$10:$H$22,MATCH(G$4,Prices!$B$10:$B$22,0))*INDEX(Prices!$G$10:$G$22,MATCH(G$4,Prices!$B$10:$B$22,0))/1000000+(D6/Assumptions!$B$30)*Assumptions!$B$31*INDEX(Prices!$H$10:$H$22,MATCH(G$4,Prices!$B$10:$B$22,0))*INDEX(Prices!$F$10:$F$22,MATCH(G$4,Prices!$B$10:$B$22,0))/1000000 -> 2.175 | H6: =E6*INDEX(Prices!$H$10:$H$22,MATCH(H$4,Prices!$B$10:$B$22,0))*INDEX(Prices!$G$10:$G$22,MATCH(H$4,Prices!$B$10:$B$22,0))/1000000+(D6/Assumptions!$B$30)*Assumptions!$B$31*INDEX(Prices!$H$10:$H$22,MATCH(H$4,Prices!$B$10:$B$22,0))*INDEX(Prices!$F$10:$F$22,MATCH(H$4,Prices!$B$10:$B$22,0))/1000000 -> 5.15 | I6: =E6*INDEX(Prices!$H$10:$H$22,MATCH(I$4,Prices!$B$10:$B$22,0))*INDEX(Prices!$G$10:$G$22,MATCH(I$4,Prices!$B$10:$B$22,0))/1000000+(D6/Assumptions!$B$30)*Assumptions!$B$31*INDEX(Prices!$H$10:$H$22,MATCH(I$4,Prices!$B$10:$B$22,0))*INDEX(Prices!$F$10:$F$22,MATCH(I$4,Prices!$B$10:$B$22,0))/1000000 -> 0.515
A7: Heavy — a real top-up | B7: 5000 | C7: 2 | D7: =B7*C7 -> 10000 | E7: =D7*Assumptions!$B$29 -> 8000000 | F7: =E7*INDEX(Prices!$H$10:$H$22,MATCH(F$4,Prices!$B$10:$B$22,0))*INDEX(Prices!$G$10:$G$22,MATCH(F$4,Prices!$B$10:$B$22,0))/1000000+(D7/Assumptions!$B$30)*Assumptions!$B$31*INDEX(Prices!$H$10:$H$22,MATCH(F$4,Prices!$B$10:$B$22,0))*INDEX(Prices!$F$10:$F$22,MATCH(F$4,Prices!$B$10:$B$22,0))/1000000 -> 56.55 | G7: =E7*INDEX(Prices!$H$10:$H$22,MATCH(G$4,Prices!$B$10:$B$22,0))*INDEX(Prices!$G$10:$G$22,MATCH(G$4,Prices!$B$10:$B$22,0))/1000000+(D7/Assumptions!$B$30)*Assumptions!$B$31*INDEX(Prices!$H$10:$H$22,MATCH(G$4,Prices!$B$10:$B$22,0))*INDEX(Prices!$F$10:$F$22,MATCH(G$4,Prices!$B$10:$B$22,0))/1000000 -> 21.75 | H7: =E7*INDEX(Prices!$H$10:$H$22,MATCH(H$4,Prices!$B$10:$B$22,0))*INDEX(Prices!$G$10:$G$22,MATCH(H$4,Prices!$B$10:$B$22,0))/1000000+(D7/Assumptions!$B$30)*Assumptions!$B$31*INDEX(Prices!$H$10:$H$22,MATCH(H$4,Prices!$B$10:$B$22,0))*INDEX(Prices!$F$10:$F$22,MATCH(H$4,Prices!$B$10:$B$22,0))/1000000 -> 51.5 | I7: =E7*INDEX(Prices!$H$10:$H$22,MATCH(I$4,Prices!$B$10:$B$22,0))*INDEX(Prices!$G$10:$G$22,MATCH(I$4,Prices!$B$10:$B$22,0))/1000000+(D7/Assumptions!$B$30)*Assumptions!$B$31*INDEX(Prices!$H$10:$H$22,MATCH(I$4,Prices!$B$10:$B$22,0))*INDEX(Prices!$F$10:$F$22,MATCH(I$4,Prices!$B$10:$B$22,0))/1000000 -> 5.15
A9: Read across a row, not down a column. At Base the model choice is worth a few dollars a cycle — not a reason to accept weaker training text. At Heavy it starts to matter.
